[
    {
      "title": "English Calculator",
      "imageSrc": "projects/SmartCal.gif",
      "description": "Calculator application utilizing Google's speech recognition library  in Python for hands-free arithmetic.",
      "skills": ["Python"],
      "demo": "'../../../public/SmartCal.mp4'",
      "source": "https://github.com/ChimpanzEatingGrades/EnglishCalculator"
    },
    {
      "title": "Fisbuk",
      "imageSrc": "projects/fisbuk.png",
      "description": "A multi-page website styled and programmed in vanilla CSS and JavaScript. Includes computational and practical functionalities such as a tax calculator, .",
      "skills": ["HTML", "CSS", "JavaScript"],
      "demo": "https://chimpanzeatinggrades.github.io/CS1130/",
      "source": "https://github.com/ChimpanzEatingGrades/CS1130"
    }
  ]
  